odoo/addons/l10n_it_asset_management/README.rst
odoo/addons/l10n_it_asset_management/__init__.py
odoo/addons/l10n_it_asset_management/__manifest__.py
odoo/addons/l10n_it_asset_management/data/asset_data.xml
odoo/addons/l10n_it_asset_management/data/ir_cron.xml
odoo/addons/l10n_it_asset_management/i18n/assets_management.pot
odoo/addons/l10n_it_asset_management/i18n/it.po
odoo/addons/l10n_it_asset_management/i18n/l10n_it_asset_management.pot
odoo/addons/l10n_it_asset_management/models/__init__.py
odoo/addons/l10n_it_asset_management/models/account_account.py
odoo/addons/l10n_it_asset_management/models/account_fiscal_year.py
odoo/addons/l10n_it_asset_management/models/account_journal.py
odoo/addons/l10n_it_asset_management/models/account_move.py
odoo/addons/l10n_it_asset_management/models/account_move_line.py
odoo/addons/l10n_it_asset_management/models/asset.py
odoo/addons/l10n_it_asset_management/models/asset_accounting_info.py
odoo/addons/l10n_it_asset_management/models/asset_category.py
odoo/addons/l10n_it_asset_management/models/asset_category_depreciation_type.py
odoo/addons/l10n_it_asset_management/models/asset_compute_depreciable_amount.py
odoo/addons/l10n_it_asset_management/models/asset_depreciation.py
odoo/addons/l10n_it_asset_management/models/asset_depreciation_line.py
odoo/addons/l10n_it_asset_management/models/asset_depreciation_line_type.py
odoo/addons/l10n_it_asset_management/models/asset_depreciation_mode.py
odoo/addons/l10n_it_asset_management/models/asset_depreciation_mode_line.py
odoo/addons/l10n_it_asset_management/models/asset_depreciation_type.py
odoo/addons/l10n_it_asset_management/models/asset_tag.py
odoo/addons/l10n_it_asset_management/readme/CONTRIBUTORS.md
odoo/addons/l10n_it_asset_management/readme/DESCRIPTION.md
odoo/addons/l10n_it_asset_management/readme/USAGE.md
odoo/addons/l10n_it_asset_management/report/__init__.py
odoo/addons/l10n_it_asset_management/report/asset_journal.py
odoo_addon_l10n_it_asset_management-18.0.1.0.0.2.dist-info/METADATA
odoo_addon_l10n_it_asset_management-18.0.1.0.0.2.dist-info/WHEEL
odoo_addon_l10n_it_asset_management-18.0.1.0.0.2.dist-info/top_level.txt
odoo_addon_l10n_it_asset_management-18.0.1.0.0.2.dist-info/RECORD
