Metadata-Version: 2.1
Name: odoo-addon-l10n_it_asset_management
Version: 18.0.1.0.0.2
Requires-Python: >=3.10
Requires-Dist: odoo-addon-account_financial_report==18.0.*
Requires-Dist: odoo-addon-account_fiscal_year==18.0.*
Requires-Dist: odoo==18.0.*
Summary: Gestione Cespiti
Home-page: https://github.com/OCA/l10n-italy
License: AGPL-3
Author: Openforce, Odoo Community Association (OCA)
Author-email: support@odoo-community.org
Classifier: Programming Language :: Python
Classifier: Framework :: Odoo
Classifier: Framework :: Odoo :: 18.0
Classifier: License :: OSI Approved :: GNU Affero General Public License v3
Classifier: Development Status :: 4 - Beta
